record_and_play_pynput/__init__.py
record_and_play_pynput/cli.py
record_and_play_pynput/config.py
record_and_play_pynput/data/test_recording.json
record_and_play_pynput/play.py
record_and_play_pynput/record.py
record_and_play_pynput/utils.py
record_and_play_pynput-0.1.2.dist-info/LICENSE
record_and_play_pynput-0.1.2.dist-info/METADATA
record_and_play_pynput-0.1.2.dist-info/WHEEL
record_and_play_pynput-0.1.2.dist-info/entry_points.txt
record_and_play_pynput-0.1.2.dist-info/RECORD
