Metadata-Version: 2.1
Name: record-and-play-pynput
Version: 0.1.2
Summary: A tool to record and play back keyboard and mouse inputs.
License: MIT
Author: George Jensen
Requires-Python: >=3.10,<4.0
Classifier: License :: OSI Approved :: MIT License
Classifier: Programming Language :: Python :: 3
Classifier: Programming Language :: Python :: 3.10
Classifier: Programming Language :: Python :: 3.11
Classifier: Programming Language :: Python :: 3.12
Requires-Dist: pynput (>=1.7.7,<2.0.0)
